aibridgecore/__init__.py
aibridgecore/exceptions.py
aibridgecore/setconfig.py
aibridgecore/ai_services/__init__.py
aibridgecore/ai_services/ai21labs_text.py
aibridgecore/ai_services/ai_abstraction.py
aibridgecore/ai_services/ai_services_response.py
aibridgecore/ai_services/alibaba_services.py
aibridgecore/ai_services/anthropic_ai.py
aibridgecore/ai_services/cohere_llm.py
aibridgecore/ai_services/deepseek_services.py
aibridgecore/ai_services/geminin_services.py
aibridgecore/ai_services/grok_services.py
aibridgecore/ai_services/image_optimisaton.py
aibridgecore/ai_services/kimi_services.py
aibridgecore/ai_services/mistral_services.py
aibridgecore/ai_services/ollama_services.py
aibridgecore/ai_services/openai_images.py
aibridgecore/ai_services/openai_services.py
aibridgecore/ai_services/process_mq.py
aibridgecore/ai_services/stable_diffusion_image.py
aibridgecore/constant/__init__.py
aibridgecore/constant/common.py
aibridgecore/constant/constant.py
aibridgecore/database/__init__.py
aibridgecore/database/db_layer.py
aibridgecore/database/no_sql_service.py
aibridgecore/database/session.py
aibridgecore/database/sql_service.py
aibridgecore/database/table_oprations.py
aibridgecore/database/models/__init__.py
aibridgecore/database/models/ai_response.py
aibridgecore/database/models/prompts.py
aibridgecore/database/models/variables.py
aibridgecore/output_validation/__init__.py
aibridgecore/output_validation/active_validator.py
aibridgecore/output_validation/convertors.py
aibridgecore/output_validation/validations.py
aibridgecore/prompts/__init__.py
aibridgecore/prompts/prompt_completion.py
aibridgecore/prompts/prompts_save.py
aibridgecore/prompts/prompts_varibales.py
aibridgecore/queue_integration/__init__.py
aibridgecore/queue_integration/assign_queue.py
aibridgecore/queue_integration/message_queue.py
aibridgecore/queue_integration/queue_model.py
aibridgecore/queue_integration/response_class.py
aibridgecore-1.4.1.dist-info/licenses/LICENSE
aibridgecore-1.4.1.dist-info/METADATA
aibridgecore-1.4.1.dist-info/WHEEL
aibridgecore-1.4.1.dist-info/top_level.txt
aibridgecore-1.4.1.dist-info/RECORD
